[
    {
        "user": "U01GHGN71UL",
        "type": "message",
        "ts": "1689073344.344669",
        "client_msg_id": "5f996e85-9298-4dfa-ad80-fea144a33808",
        "text": "Yep, very interesting! Especially nice to hear about wildDISCO in a Wildsheet comunity..!Btw, if anyone would like to discuss the paper (in a kind of JC format) let me know and we can organize a Zoom meeting!",
        "team": "T01FQQGKPLH",
        "user_team": "T01FQQGKPLH",
        "source_team": "T01FQQGKPLH",
        "user_profile": {
            "avatar_hash": "d6aed3d2c44f",
            "image_72": "https:\/\/avatars.slack-edge.com\/2020-12-09\/1567510911348_d6aed3d2c44f9bdc9863_72.jpg",
            "first_name": "Alessandro",
            "real_name": "Alessandro Ciccarelli",
            "display_name": "Alessandro Ciccarelli",
            "team": "T01FQQGKPLH",
            "name": "alessandro.ciccarelli",
            "is_restricted": false,
            "is_ultra_restricted": false
        },
        "thread_ts": "1689016789.883589",
        "parent_user_id": "U04M5SGCM5J",
        "blocks": [
            {
                "type": "rich_text",
                "block_id": "ejKsI",
                "elements": [
                    {
                        "type": "rich_text_section",
                        "elements": [
                            {
                                "type": "text",
                                "text": "Yep, very interesting! Especially nice to hear about wildDISCO in a Wildsheet comunity..!Btw, if anyone would like to discuss the paper (in a kind of JC format) let me know and we can organize a Zoom meeting!"
                            }
                        ]
                    }
                ]
            }
        ],
        "reactions": [
            {
                "name": "laughing",
                "users": [
                    "U04UTRSQXNE"
                ],
                "count": 1
            },
            {
                "name": "raised_hands",
                "users": [
                    "U04UNBGETHC"
                ],
                "count": 1
            }
        ]
    },
    {
        "user": "U04UTRSQXNE",
        "type": "message",
        "ts": "1689074154.728759",
        "client_msg_id": "6f45d392-ded2-4fcf-b546-414396ecb6f1",
        "text": "I would love to join the discussion if it happens :blush:",
        "team": "T01FQQGKPLH",
        "user_team": "T01FQQGKPLH",
        "source_team": "T01FQQGKPLH",
        "user_profile": {
            "avatar_hash": "ef732a54ec22",
            "image_72": "https:\/\/avatars.slack-edge.com\/2023-03-20\/4992512058769_ef732a54ec2204fdabcc_72.jpg",
            "first_name": "Sunny",
            "real_name": "Sunny Keqing Dai",
            "display_name": "Sunny",
            "team": "T01FQQGKPLH",
            "name": "keqingdai",
            "is_restricted": false,
            "is_ultra_restricted": false
        },
        "thread_ts": "1689016789.883589",
        "parent_user_id": "U04M5SGCM5J",
        "blocks": [
            {
                "type": "rich_text",
                "block_id": "dEx9",
                "elements": [
                    {
                        "type": "rich_text_section",
                        "elements": [
                            {
                                "type": "text",
                                "text": "I would love to join the discussion if it happens "
                            },
                            {
                                "type": "emoji",
                                "name": "blush",
                                "unicode": "1f60a"
                            }
                        ]
                    }
                ]
            }
        ]
    }
]