[
    {
        "user": "U01JZAQRXHN",
        "type": "message",
        "ts": "1610361601.000100",
        "client_msg_id": "b3185437-e08d-495e-9f89-7c2099bbbbbb",
        "text": "I am not very good at the wiki things so if you cna help me out or anybody from the community I am happy to upload all my stuff..stay safe",
        "team": "T01FQQGKPLH",
        "user_team": "T01FQQGKPLH",
        "source_team": "T01FQQGKPLH",
        "user_profile": {
            "avatar_hash": "2074bddfd928",
            "image_72": "https:\/\/avatars.slack-edge.com\/2021-01-08\/1618435752197_2074bddfd92855c3919f_72.jpg",
            "first_name": "",
            "real_name": "Emmanuel Reynaud",
            "display_name": "Emmanuel Reynaud",
            "team": "T01FQQGKPLH",
            "name": "emmanuel.reynaud",
            "is_restricted": false,
            "is_ultra_restricted": false
        },
        "thread_ts": "1610105751.001100",
        "parent_user_id": "U01JZAQRXHN",
        "blocks": [
            {
                "type": "rich_text",
                "block_id": "txUM",
                "elements": [
                    {
                        "type": "rich_text_section",
                        "elements": [
                            {
                                "type": "text",
                                "text": "I am not very good at the wiki things so if you cna help me out or anybody from the community I am happy to upload all my stuff..stay safe"
                            }
                        ]
                    }
                ]
            }
        ]
    }
]